LICENCE.txt
README.md
setup.py
pixlr_private_api/__init__.py
pixlr_private_api/main.py
pixlr_private_api.egg-info/PKG-INFO
pixlr_private_api.egg-info/SOURCES.txt
pixlr_private_api.egg-info/dependency_links.txt
pixlr_private_api.egg-info/requires.txt
pixlr_private_api.egg-info/top_level.txt