Metadata-Version: 2.1
Name: pixlr_private_api
Version: 0.1.2
Summary: A Python Package to Generate Images with http://pixlr.com programmatically.
Home-page: https://github.com/Automa-Automations/pixlr-private-api
Author: Simon Ferns
Author-email: business@simonferns.com
License: MIT
Keywords: temp-email automation email
Classifier: Development Status :: 3 - Alpha
Classifier: Intended Audience :: Developers
Classifier: License :: OSI Approved :: MIT License
Classifier: Programming Language :: Python :: 3
Classifier: Programming Language :: Python :: 3.6
Classifier: Programming Language :: Python :: 3.7
Classifier: Programming Language :: Python :: 3.8
Classifier: Programming Language :: Python :: 3.9
Classifier: Programming Language :: Python :: 3.10
Classifier: Programming Language :: Python :: 3.11
Classifier: Programming Language :: Python :: 3.12
Classifier: Operating System :: OS Independent
License-File: LICENCE.txt
Requires-Dist: requests
Requires-Dist: temp_email_automa
Requires-Dist: pillow
